gym_yumi/__init__.py
gym_yumi/env/__init__.py
gym_yumi/env/yumi_env.py
gym_yumi-0.0.1.dist-info/METADATA
gym_yumi-0.0.1.dist-info/WHEEL
gym_yumi-0.0.1.dist-info/top_level.txt
gym_yumi-0.0.1.dist-info/RECORD
