Metadata-Version: 2.1
Name: gym-yumi
Version: 0.0.1
Summary: A OpenAI Gym Env for Yumi
Home-page: UNKNOWN
License: UNKNOWN
Platform: UNKNOWN
Requires-Dist: gym
